__about__.py
credentials_lemm_ee.py
credentials_thesanewriter.py
src/__init__.py
src/lemmy_mod_bot.py
src/examples/__init__.py
src/examples/credentials_template.py
src/examples/example.py
src/models/__init__.py
src/models/bag_of_words.py
lemmy_mod_bot-0.0.5.dist-info/METADATA
lemmy_mod_bot-0.0.5.dist-info/WHEEL
lemmy_mod_bot-0.0.5.dist-info/licenses/LICENCE.txt
lemmy_mod_bot-0.0.5.dist-info/RECORD
