Metadata-Version: 2.1
Name: lemmy_mod_bot
Version: 0.0.5
Summary: lemmy_mod_bot is a Lemmy Mod Bot written in Python
Project-URL: Homepage, https://github.com/noenfugler/LemmyModBot
Project-URL: Bug Tracker, https://github.com/noenfugler/LemmyModBot/issues
Author-email: noenfugler <noenfugler@greenwolf.com.au>
License-File: LICENCE.txt
Classifier: License :: OSI Approved :: GNU General Public License v3 (GPLv3)
Classifier: Operating System :: OS Independent
Classifier: Programming Language :: Python :: 3
Requires-Python: >=3.7
